interdoc/__init__.py
interdoc/__main__.py
interdoc/app.py
interdoc/cli.py
interdoc-0.1.0.dist-info/entry_points.txt
interdoc-0.1.0.dist-info/LICENSE
interdoc-0.1.0.dist-info/WHEEL
interdoc-0.1.0.dist-info/METADATA
interdoc-0.1.0.dist-info/RECORD
