Metadata-Version: 2.1
Name: interdoc
Version: 0.1.0
Summary: 
Author: Interdoc contributors
Author-email: metatooling@users.noreply.github.com
Requires-Python: >=3.7,<4.0
Classifier: Programming Language :: Python :: 3
Classifier: Programming Language :: Python :: 3.7
Provides-Extra: docs
Requires-Dist: attrs (==19.1.0)
Requires-Dist: click (==7.0)
